{
  "updated": "2026-06-02",
  "events": [
    {
      "leadId": "hist-0",
      "repName": "Andrew Funk",
      "status": "SGCA",
      "isCA": true,
      "date": "2026-05-29",
      "address": "",
      "eventType": "historical_import",
      "ts": "2026-05-29T00:00:00Z"
    },
    {
      "leadId": "hist-1",
      "repName": "Michael McCarthy",
      "status": "SGCA",
      "isCA": true,
      "date": "2026-05-28",
      "address": "",
      "eventType": "historical_import",
      "ts": "2026-05-28T00:00:00Z"
    },
    {
      "leadId": "hist-2",
      "repName": "Andrew Funk",
      "status": "SGCA",
      "isCA": true,
      "date": "2026-05-28",
      "address": "",
      "eventType": "historical_import",
      "ts": "2026-05-28T00:00:00Z"
    },
    {
      "leadId": "hist-3",
      "repName": "Michael McCarthy",
      "status": "ICA",
      "isCA": true,
      "date": "2026-05-28",
      "address": "",
      "eventType": "historical_import",
      "ts": "2026-05-28T00:00:00Z"
    },
    {
      "leadId": "hist-4",
      "repName": "Marc Mitchell",
      "status": "ICA",
      "isCA": true,
      "date": "2026-05-26",
      "address": "",
      "eventType": "historical_import",
      "ts": "2026-05-26T00:00:00Z"
    },
    {
      "leadId": "hist-5",
      "repName": "Andrew Funk",
      "status": "SGCA",
      "isCA": true,
      "date": "2026-05-26",
      "address": "",
      "eventType": "historical_import",
      "ts": "2026-05-26T00:00:00Z"
    },
    {
      "leadId": "hist-6",
      "repName": "Harvey Shoemaker",
      "status": "SGCA",
      "isCA": true,
      "date": "2026-05-26",
      "address": "",
      "eventType": "historical_import",
      "ts": "2026-05-26T00:00:00Z"
    },
    {
      "leadId": "hist-7",
      "repName": "Harvey Shoemaker",
      "status": "SGCA",
      "isCA": true,
      "date": "2026-05-26",
      "address": "",
      "eventType": "historical_import",
      "ts": "2026-05-26T00:00:00Z"
    },
    {
      "leadId": "hist-8",
      "repName": "Andrew Prickel",
      "status": "ICA",
      "isCA": true,
      "date": "2026-05-26",
      "address": "",
      "eventType": "historical_import",
      "ts": "2026-05-26T00:00:00Z"
    },
    {
      "leadId": "hist-9",
      "repName": "Harvey Shoemaker",
      "status": "ICA",
      "isCA": true,
      "date": "2026-05-26",
      "address": "",
      "eventType": "historical_import",
      "ts": "2026-05-26T00:00:00Z"
    },
    {
      "leadId": "hist-10",
      "repName": "Andrew Funk",
      "status": "SGCA",
      "isCA": true,
      "date": "2026-05-29",
      "address": "",
      "eventType": "historical_import",
      "ts": "2026-05-29T00:00:00Z"
    },
    {
      "leadId": "hist-11",
      "repName": "Michael McCarthy",
      "status": "SGCA",
      "isCA": true,
      "date": "2026-05-28",
      "address": "",
      "eventType": "historical_import",
      "ts": "2026-05-28T00:00:00Z"
    },
    {
      "leadId": "hist-12",
      "repName": "Andrew Funk",
      "status": "SGCA",
      "isCA": true,
      "date": "2026-05-28",
      "address": "",
      "eventType": "historical_import",
      "ts": "2026-05-28T00:00:00Z"
    },
    {
      "leadId": "hist-13",
      "repName": "Michael McCarthy",
      "status": "ICA",
      "isCA": true,
      "date": "2026-05-28",
      "address": "",
      "eventType": "historical_import",
      "ts": "2026-05-28T00:00:00Z"
    },
    {
      "leadId": "hist-14",
      "repName": "Marc Mitchell",
      "status": "ICA",
      "isCA": true,
      "date": "2026-05-26",
      "address": "",
      "eventType": "historical_import",
      "ts": "2026-05-26T00:00:00Z"
    },
    {
      "leadId": "hist-15",
      "repName": "Andrew Funk",
      "status": "SGCA",
      "isCA": true,
      "date": "2026-05-26",
      "address": "",
      "eventType": "historical_import",
      "ts": "2026-05-26T00:00:00Z"
    },
    {
      "leadId": "hist-16",
      "repName": "Harvey Shoemaker",
      "status": "SGCA",
      "isCA": true,
      "date": "2026-05-26",
      "address": "",
      "eventType": "historical_import",
      "ts": "2026-05-26T00:00:00Z"
    },
    {
      "leadId": "hist-17",
      "repName": "Harvey Shoemaker",
      "status": "SGCA",
      "isCA": true,
      "date": "2026-05-26",
      "address": "",
      "eventType": "historical_import",
      "ts": "2026-05-26T00:00:00Z"
    },
    {
      "leadId": "hist-18",
      "repName": "Andrew Prickel",
      "status": "ICA",
      "isCA": true,
      "date": "2026-05-26",
      "address": "",
      "eventType": "historical_import",
      "ts": "2026-05-26T00:00:00Z"
    },
    {
      "leadId": "hist-19",
      "repName": "Harvey Shoemaker",
      "status": "ICA",
      "isCA": true,
      "date": "2026-05-26",
      "address": "",
      "eventType": "historical_import",
      "ts": "2026-05-26T00:00:00Z"
    },
    {
      "leadId": "hist-20",
      "repName": "Andrew Funk",
      "status": "SGCA",
      "isCA": true,
      "date": "2026-05-29",
      "address": "",
      "eventType": "historical_import",
      "ts": "2026-05-29T00:00:00Z"
    },
    {
      "leadId": "hist-21",
      "repName": "Michael McCarthy",
      "status": "SGCA",
      "isCA": true,
      "date": "2026-05-28",
      "address": "",
      "eventType": "historical_import",
      "ts": "2026-05-28T00:00:00Z"
    },
    {
      "leadId": "hist-22",
      "repName": "Andrew Funk",
      "status": "SGCA",
      "isCA": true,
      "date": "2026-05-28",
      "address": "",
      "eventType": "historical_import",
      "ts": "2026-05-28T00:00:00Z"
    },
    {
      "leadId": "hist-23",
      "repName": "Michael McCarthy",
      "status": "ICA",
      "isCA": true,
      "date": "2026-05-28",
      "address": "",
      "eventType": "historical_import",
      "ts": "2026-05-28T00:00:00Z"
    },
    {
      "leadId": "hist-24",
      "repName": "Marc Mitchell",
      "status": "ICA",
      "isCA": true,
      "date": "2026-05-26",
      "address": "",
      "eventType": "historical_import",
      "ts": "2026-05-26T00:00:00Z"
    },
    {
      "leadId": "hist-25",
      "repName": "Andrew Funk",
      "status": "SGCA",
      "isCA": true,
      "date": "2026-05-26",
      "address": "",
      "eventType": "historical_import",
      "ts": "2026-05-26T00:00:00Z"
    },
    {
      "leadId": "hist-26",
      "repName": "Harvey Shoemaker",
      "status": "SGCA",
      "isCA": true,
      "date": "2026-05-26",
      "address": "",
      "eventType": "historical_import",
      "ts": "2026-05-26T00:00:00Z"
    },
    {
      "leadId": "hist-27",
      "repName": "Harvey Shoemaker",
      "status": "SGCA",
      "isCA": true,
      "date": "2026-05-26",
      "address": "",
      "eventType": "historical_import",
      "ts": "2026-05-26T00:00:00Z"
    },
    {
      "leadId": "hist-28",
      "repName": "Andrew Prickel",
      "status": "ICA",
      "isCA": true,
      "date": "2026-05-26",
      "address": "",
      "eventType": "historical_import",
      "ts": "2026-05-26T00:00:00Z"
    },
    {
      "leadId": "hist-29",
      "repName": "Harvey Shoemaker",
      "status": "ICA",
      "isCA": true,
      "date": "2026-05-26",
      "address": "",
      "eventType": "historical_import",
      "ts": "2026-05-26T00:00:00Z"
    },
    {
      "leadId": "hist-30",
      "repName": "Andrew Funk",
      "status": "SGCA",
      "isCA": true,
      "date": "2026-05-29",
      "address": "",
      "eventType": "historical_import",
      "ts": "2026-05-29T00:00:00Z"
    },
    {
      "leadId": "hist-31",
      "repName": "Michael McCarthy",
      "status": "SGCA",
      "isCA": true,
      "date": "2026-05-28",
      "address": "",
      "eventType": "historical_import",
      "ts": "2026-05-28T00:00:00Z"
    },
    {
      "leadId": "hist-32",
      "repName": "Andrew Funk",
      "status": "SGCA",
      "isCA": true,
      "date": "2026-05-28",
      "address": "",
      "eventType": "historical_import",
      "ts": "2026-05-28T00:00:00Z"
    },
    {
      "leadId": "hist-33",
      "repName": "Michael McCarthy",
      "status": "ICA",
      "isCA": true,
      "date": "2026-05-28",
      "address": "",
      "eventType": "historical_import",
      "ts": "2026-05-28T00:00:00Z"
    },
    {
      "leadId": "hist-34",
      "repName": "Marc Mitchell",
      "status": "ICA",
      "isCA": true,
      "date": "2026-05-26",
      "address": "",
      "eventType": "historical_import",
      "ts": "2026-05-26T00:00:00Z"
    },
    {
      "leadId": "hist-35",
      "repName": "Andrew Funk",
      "status": "SGCA",
      "isCA": true,
      "date": "2026-05-26",
      "address": "",
      "eventType": "historical_import",
      "ts": "2026-05-26T00:00:00Z"
    },
    {
      "leadId": "hist-36",
      "repName": "Harvey Shoemaker",
      "status": "SGCA",
      "isCA": true,
      "date": "2026-05-26",
      "address": "",
      "eventType": "historical_import",
      "ts": "2026-05-26T00:00:00Z"
    },
    {
      "leadId": "hist-37",
      "repName": "Harvey Shoemaker",
      "status": "SGCA",
      "isCA": true,
      "date": "2026-05-26",
      "address": "",
      "eventType": "historical_import",
      "ts": "2026-05-26T00:00:00Z"
    },
    {
      "leadId": "hist-38",
      "repName": "Andrew Prickel",
      "status": "ICA",
      "isCA": true,
      "date": "2026-05-26",
      "address": "",
      "eventType": "historical_import",
      "ts": "2026-05-26T00:00:00Z"
    },
    {
      "leadId": "hist-39",
      "repName": "Harvey Shoemaker",
      "status": "ICA",
      "isCA": true,
      "date": "2026-05-26",
      "address": "",
      "eventType": "historical_import",
      "ts": "2026-05-26T00:00:00Z"
    },
    {
      "leadId": "hist-40",
      "repName": "Andrew Funk",
      "status": "SGCA",
      "isCA": true,
      "date": "2026-05-29",
      "address": "",
      "eventType": "historical_import",
      "ts": "2026-05-29T00:00:00Z"
    },
    {
      "leadId": "hist-41",
      "repName": "Michael McCarthy",
      "status": "SGCA",
      "isCA": true,
      "date": "2026-05-28",
      "address": "",
      "eventType": "historical_import",
      "ts": "2026-05-28T00:00:00Z"
    },
    {
      "leadId": "hist-42",
      "repName": "Andrew Funk",
      "status": "SGCA",
      "isCA": true,
      "date": "2026-05-28",
      "address": "",
      "eventType": "historical_import",
      "ts": "2026-05-28T00:00:00Z"
    },
    {
      "leadId": "hist-43",
      "repName": "Michael McCarthy",
      "status": "ICA",
      "isCA": true,
      "date": "2026-05-28",
      "address": "",
      "eventType": "historical_import",
      "ts": "2026-05-28T00:00:00Z"
    },
    {
      "leadId": "hist-44",
      "repName": "Marc Mitchell",
      "status": "ICA",
      "isCA": true,
      "date": "2026-05-26",
      "address": "",
      "eventType": "historical_import",
      "ts": "2026-05-26T00:00:00Z"
    },
    {
      "leadId": "hist-45",
      "repName": "Andrew Funk",
      "status": "SGCA",
      "isCA": true,
      "date": "2026-05-26",
      "address": "",
      "eventType": "historical_import",
      "ts": "2026-05-26T00:00:00Z"
    },
    {
      "leadId": "hist-46",
      "repName": "Harvey Shoemaker",
      "status": "SGCA",
      "isCA": true,
      "date": "2026-05-26",
      "address": "",
      "eventType": "historical_import",
      "ts": "2026-05-26T00:00:00Z"
    },
    {
      "leadId": "hist-47",
      "repName": "Harvey Shoemaker",
      "status": "SGCA",
      "isCA": true,
      "date": "2026-05-26",
      "address": "",
      "eventType": "historical_import",
      "ts": "2026-05-26T00:00:00Z"
    },
    {
      "leadId": "hist-48",
      "repName": "Andrew Prickel",
      "status": "ICA",
      "isCA": true,
      "date": "2026-05-26",
      "address": "",
      "eventType": "historical_import",
      "ts": "2026-05-26T00:00:00Z"
    },
    {
      "leadId": "hist-49",
      "repName": "Harvey Shoemaker",
      "status": "ICA",
      "isCA": true,
      "date": "2026-05-26",
      "address": "",
      "eventType": "historical_import",
      "ts": "2026-05-26T00:00:00Z"
    },
    {
      "leadId": "hist-50",
      "repName": "Andrew Funk",
      "status": "SGCA",
      "isCA": true,
      "date": "2026-05-29",
      "address": "",
      "eventType": "historical_import",
      "ts": "2026-05-29T00:00:00Z"
    },
    {
      "leadId": "hist-51",
      "repName": "Michael McCarthy",
      "status": "SGCA",
      "isCA": true,
      "date": "2026-05-28",
      "address": "",
      "eventType": "historical_import",
      "ts": "2026-05-28T00:00:00Z"
    },
    {
      "leadId": "hist-52",
      "repName": "Andrew Funk",
      "status": "SGCA",
      "isCA": true,
      "date": "2026-05-28",
      "address": "",
      "eventType": "historical_import",
      "ts": "2026-05-28T00:00:00Z"
    },
    {
      "leadId": "hist-53",
      "repName": "Michael McCarthy",
      "status": "ICA",
      "isCA": true,
      "date": "2026-05-28",
      "address": "",
      "eventType": "historical_import",
      "ts": "2026-05-28T00:00:00Z"
    },
    {
      "leadId": "hist-54",
      "repName": "Marc Mitchell",
      "status": "ICA",
      "isCA": true,
      "date": "2026-05-26",
      "address": "",
      "eventType": "historical_import",
      "ts": "2026-05-26T00:00:00Z"
    },
    {
      "leadId": "hist-55",
      "repName": "Andrew Funk",
      "status": "SGCA",
      "isCA": true,
      "date": "2026-05-26",
      "address": "",
      "eventType": "historical_import",
      "ts": "2026-05-26T00:00:00Z"
    },
    {
      "leadId": "hist-56",
      "repName": "Harvey Shoemaker",
      "status": "SGCA",
      "isCA": true,
      "date": "2026-05-26",
      "address": "",
      "eventType": "historical_import",
      "ts": "2026-05-26T00:00:00Z"
    },
    {
      "leadId": "hist-57",
      "repName": "Harvey Shoemaker",
      "status": "SGCA",
      "isCA": true,
      "date": "2026-05-26",
      "address": "",
      "eventType": "historical_import",
      "ts": "2026-05-26T00:00:00Z"
    },
    {
      "leadId": "hist-58",
      "repName": "Andrew Prickel",
      "status": "ICA",
      "isCA": true,
      "date": "2026-05-26",
      "address": "",
      "eventType": "historical_import",
      "ts": "2026-05-26T00:00:00Z"
    },
    {
      "leadId": "hist-59",
      "repName": "Harvey Shoemaker",
      "status": "ICA",
      "isCA": true,
      "date": "2026-05-26",
      "address": "",
      "eventType": "historical_import",
      "ts": "2026-05-26T00:00:00Z"
    },
    {
      "leadId": "hist-60",
      "repName": "Andrew Funk",
      "status": "SGCA",
      "isCA": true,
      "date": "2026-05-29",
      "address": "",
      "eventType": "historical_import",
      "ts": "2026-05-29T00:00:00Z"
    },
    {
      "leadId": "hist-61",
      "repName": "Michael McCarthy",
      "status": "SGCA",
      "isCA": true,
      "date": "2026-05-28",
      "address": "",
      "eventType": "historical_import",
      "ts": "2026-05-28T00:00:00Z"
    },
    {
      "leadId": "hist-62",
      "repName": "Andrew Funk",
      "status": "SGCA",
      "isCA": true,
      "date": "2026-05-28",
      "address": "",
      "eventType": "historical_import",
      "ts": "2026-05-28T00:00:00Z"
    },
    {
      "leadId": "hist-63",
      "repName": "Michael McCarthy",
      "status": "ICA",
      "isCA": true,
      "date": "2026-05-28",
      "address": "",
      "eventType": "historical_import",
      "ts": "2026-05-28T00:00:00Z"
    },
    {
      "leadId": "hist-64",
      "repName": "Marc Mitchell",
      "status": "ICA",
      "isCA": true,
      "date": "2026-05-26",
      "address": "",
      "eventType": "historical_import",
      "ts": "2026-05-26T00:00:00Z"
    },
    {
      "leadId": "hist-65",
      "repName": "Andrew Funk",
      "status": "SGCA",
      "isCA": true,
      "date": "2026-05-26",
      "address": "",
      "eventType": "historical_import",
      "ts": "2026-05-26T00:00:00Z"
    },
    {
      "leadId": "hist-66",
      "repName": "Harvey Shoemaker",
      "status": "SGCA",
      "isCA": true,
      "date": "2026-05-26",
      "address": "",
      "eventType": "historical_import",
      "ts": "2026-05-26T00:00:00Z"
    },
    {
      "leadId": "hist-67",
      "repName": "Harvey Shoemaker",
      "status": "SGCA",
      "isCA": true,
      "date": "2026-05-26",
      "address": "",
      "eventType": "historical_import",
      "ts": "2026-05-26T00:00:00Z"
    },
    {
      "leadId": "hist-68",
      "repName": "Andrew Prickel",
      "status": "ICA",
      "isCA": true,
      "date": "2026-05-26",
      "address": "",
      "eventType": "historical_import",
      "ts": "2026-05-26T00:00:00Z"
    },
    {
      "leadId": "hist-69",
      "repName": "Harvey Shoemaker",
      "status": "ICA",
      "isCA": true,
      "date": "2026-05-26",
      "address": "",
      "eventType": "historical_import",
      "ts": "2026-05-26T00:00:00Z"
    },
    {
      "leadId": "47173",
      "repName": "David Kerns",
      "status": "NO ANSWER",
      "isCA": false,
      "date": "2026-06-02",
      "address": "11105 Richland Valley Dr, Great Falls, VA",
      "ts": "2026-06-02T15:06:30.373Z"
    },
    {
      "leadId": "47173",
      "repName": "David Kerns",
      "status": "INSPECTED",
      "isCA": false,
      "date": "2026-06-02",
      "address": "11105 Richland Valley Dr, Great Falls, VA",
      "ts": "2026-06-02T15:08:40.273Z"
    },
    {
      "leadId": "47178",
      "repName": "Andrew Funk",
      "status": "NO ANSWER",
      "isCA": false,
      "date": "2026-06-02",
      "address": "4594 Clearwater Ct, Dumfries, VA",
      "ts": "2026-06-02T15:27:00.922Z"
    },
    {
      "leadId": "47179",
      "repName": "Andrew Funk",
      "status": "NO ANSWER",
      "isCA": false,
      "date": "2026-06-02",
      "address": "4595 Clearwater Ct, Dumfries, VA",
      "ts": "2026-06-02T15:27:02.641Z"
    },
    {
      "leadId": "47181",
      "repName": "Andrew Funk",
      "status": "NO ANSWER",
      "isCA": false,
      "date": "2026-06-02",
      "address": "4592 Clearwater Ct, Dumfries, VA",
      "ts": "2026-06-02T15:30:03.147Z"
    },
    {
      "leadId": "47183",
      "repName": "Andrew Funk",
      "status": "NO ANSWER",
      "isCA": false,
      "date": "2026-06-02",
      "address": "4593 Clearwater Ct, Dumfries, VA",
      "ts": "2026-06-02T15:31:22.331Z"
    },
    {
      "leadId": "47185",
      "repName": "Harvey Shoemaker",
      "status": "NOT INTERRESTED",
      "isCA": false,
      "date": "2026-06-01",
      "address": "5325 Kipp Ct, Fairfax, VA",
      "ts": "2026-06-02T15:33:53.265Z"
    },
    {
      "leadId": "33612",
      "repName": "George Bechara",
      "status": "INSPECTED",
      "isCA": false,
      "date": "2026-06-02",
      "address": "11529 Seneca Farm Way, Great Falls, VA",
      "ts": "2026-06-02T15:38:47.828Z"
    },
    {
      "leadId": "47189",
      "repName": "George Bechara",
      "status": "INSPECTED",
      "isCA": false,
      "date": "2026-06-02",
      "address": "11303 Seneca Cir, Great Falls, VA",
      "ts": "2026-06-02T15:40:53.127Z"
    },
    {
      "leadId": "csv-door-0",
      "repName": "Harvey Shoemaker",
      "status": "No Answer",
      "isCA": false,
      "date": "2026-06-02",
      "address": "",
      "eventType": "csv_export_import",
      "ts": "2026-06-02T00:00:00Z"
    },
    {
      "leadId": "csv-door-1",
      "repName": "Harvey Shoemaker",
      "status": "No Answer",
      "isCA": false,
      "date": "2026-06-02",
      "address": "",
      "eventType": "csv_export_import",
      "ts": "2026-06-02T00:00:00Z"
    },
    {
      "leadId": "csv-door-2",
      "repName": "Harvey Shoemaker",
      "status": "No Answer",
      "isCA": false,
      "date": "2026-06-02",
      "address": "",
      "eventType": "csv_export_import",
      "ts": "2026-06-02T00:00:00Z"
    },
    {
      "leadId": "csv-door-3",
      "repName": "Harvey Shoemaker",
      "status": "No Answer",
      "isCA": false,
      "date": "2026-06-02",
      "address": "",
      "eventType": "csv_export_import",
      "ts": "2026-06-02T00:00:00Z"
    },
    {
      "leadId": "csv-door-4",
      "repName": "Harvey Shoemaker",
      "status": "No Answer",
      "isCA": false,
      "date": "2026-06-02",
      "address": "",
      "eventType": "csv_export_import",
      "ts": "2026-06-02T00:00:00Z"
    },
    {
      "leadId": "csv-door-5",
      "repName": "Harvey Shoemaker",
      "status": "No Answer",
      "isCA": false,
      "date": "2026-06-02",
      "address": "",
      "eventType": "csv_export_import",
      "ts": "2026-06-02T00:00:00Z"
    },
    {
      "leadId": "csv-door-6",
      "repName": "Harvey Shoemaker",
      "status": "No Answer",
      "isCA": false,
      "date": "2026-06-02",
      "address": "",
      "eventType": "csv_export_import",
      "ts": "2026-06-02T00:00:00Z"
    },
    {
      "leadId": "csv-door-7",
      "repName": "Harvey Shoemaker",
      "status": "No Answer",
      "isCA": false,
      "date": "2026-06-02",
      "address": "",
      "eventType": "csv_export_import",
      "ts": "2026-06-02T00:00:00Z"
    },
    {
      "leadId": "csv-door-8",
      "repName": "Harvey Shoemaker",
      "status": "No Answer",
      "isCA": false,
      "date": "2026-06-02",
      "address": "",
      "eventType": "csv_export_import",
      "ts": "2026-06-02T00:00:00Z"
    },
    {
      "leadId": "csv-door-9",
      "repName": "Harvey Shoemaker",
      "status": "No Answer",
      "isCA": false,
      "date": "2026-06-02",
      "address": "",
      "eventType": "csv_export_import",
      "ts": "2026-06-02T00:00:00Z"
    },
    {
      "leadId": "csv-door-10",
      "repName": "Harvey Shoemaker",
      "status": "No Answer",
      "isCA": false,
      "date": "2026-06-02",
      "address": "",
      "eventType": "csv_export_import",
      "ts": "2026-06-02T00:00:00Z"
    },
    {
      "leadId": "csv-door-11",
      "repName": "Harvey Shoemaker",
      "status": "No Answer",
      "isCA": false,
      "date": "2026-06-02",
      "address": "",
      "eventType": "csv_export_import",
      "ts": "2026-06-02T00:00:00Z"
    },
    {
      "leadId": "csv-door-12",
      "repName": "Harvey Shoemaker",
      "status": "No Answer",
      "isCA": false,
      "date": "2026-06-02",
      "address": "",
      "eventType": "csv_export_import",
      "ts": "2026-06-02T00:00:00Z"
    },
    {
      "leadId": "csv-door-13",
      "repName": "Harvey Shoemaker",
      "status": "No Answer",
      "isCA": false,
      "date": "2026-06-02",
      "address": "",
      "eventType": "csv_export_import",
      "ts": "2026-06-02T00:00:00Z"
    },
    {
      "leadId": "csv-door-14",
      "repName": "Harvey Shoemaker",
      "status": "No Answer",
      "isCA": false,
      "date": "2026-06-02",
      "address": "",
      "eventType": "csv_export_import",
      "ts": "2026-06-02T00:00:00Z"
    },
    {
      "leadId": "csv-door-15",
      "repName": "Harvey Shoemaker",
      "status": "No Answer",
      "isCA": false,
      "date": "2026-06-02",
      "address": "",
      "eventType": "csv_export_import",
      "ts": "2026-06-02T00:00:00Z"
    },
    {
      "leadId": "csv-door-16",
      "repName": "Harvey Shoemaker",
      "status": "No Answer",
      "isCA": false,
      "date": "2026-06-02",
      "address": "",
      "eventType": "csv_export_import",
      "ts": "2026-06-02T00:00:00Z"
    },
    {
      "leadId": "csv-door-17",
      "repName": "Harvey Shoemaker",
      "status": "No Answer",
      "isCA": false,
      "date": "2026-06-02",
      "address": "",
      "eventType": "csv_export_import",
      "ts": "2026-06-02T00:00:00Z"
    },
    {
      "leadId": "csv-door-18",
      "repName": "Harvey Shoemaker",
      "status": "No Answer",
      "isCA": false,
      "date": "2026-06-02",
      "address": "",
      "eventType": "csv_export_import",
      "ts": "2026-06-02T00:00:00Z"
    },
    {
      "leadId": "csv-door-19",
      "repName": "Harvey Shoemaker",
      "status": "No Answer",
      "isCA": false,
      "date": "2026-06-02",
      "address": "",
      "eventType": "csv_export_import",
      "ts": "2026-06-02T00:00:00Z"
    },
    {
      "leadId": "csv-door-20",
      "repName": "Harvey Shoemaker",
      "status": "No Answer",
      "isCA": false,
      "date": "2026-06-02",
      "address": "",
      "eventType": "csv_export_import",
      "ts": "2026-06-02T00:00:00Z"
    },
    {
      "leadId": "csv-door-21",
      "repName": "Harvey Shoemaker",
      "status": "No Answer",
      "isCA": false,
      "date": "2026-06-02",
      "address": "",
      "eventType": "csv_export_import",
      "ts": "2026-06-02T00:00:00Z"
    },
    {
      "leadId": "csv-door-22",
      "repName": "Harvey Shoemaker",
      "status": "No Answer",
      "isCA": false,
      "date": "2026-06-02",
      "address": "",
      "eventType": "csv_export_import",
      "ts": "2026-06-02T00:00:00Z"
    },
    {
      "leadId": "csv-door-23",
      "repName": "Harvey Shoemaker",
      "status": "No Answer",
      "isCA": false,
      "date": "2026-06-02",
      "address": "",
      "eventType": "csv_export_import",
      "ts": "2026-06-02T00:00:00Z"
    },
    {
      "leadId": "csv-door-24",
      "repName": "Harvey Shoemaker",
      "status": "No Answer",
      "isCA": false,
      "date": "2026-06-02",
      "address": "",
      "eventType": "csv_export_import",
      "ts": "2026-06-02T00:00:00Z"
    },
    {
      "leadId": "csv-door-25",
      "repName": "Harvey Shoemaker",
      "status": "No Answer",
      "isCA": false,
      "date": "2026-06-02",
      "address": "",
      "eventType": "csv_export_import",
      "ts": "2026-06-02T00:00:00Z"
    },
    {
      "leadId": "csv-door-26",
      "repName": "Harvey Shoemaker",
      "status": "No Answer",
      "isCA": false,
      "date": "2026-06-02",
      "address": "",
      "eventType": "csv_export_import",
      "ts": "2026-06-02T00:00:00Z"
    },
    {
      "leadId": "csv-door-27",
      "repName": "Harvey Shoemaker",
      "status": "No Answer",
      "isCA": false,
      "date": "2026-06-02",
      "address": "",
      "eventType": "csv_export_import",
      "ts": "2026-06-02T00:00:00Z"
    },
    {
      "leadId": "csv-door-28",
      "repName": "Harvey Shoemaker",
      "status": "No Answer",
      "isCA": false,
      "date": "2026-06-02",
      "address": "",
      "eventType": "csv_export_import",
      "ts": "2026-06-02T00:00:00Z"
    },
    {
      "leadId": "csv-door-29",
      "repName": "Harvey Shoemaker",
      "status": "No Answer",
      "isCA": false,
      "date": "2026-06-02",
      "address": "",
      "eventType": "csv_export_import",
      "ts": "2026-06-02T00:00:00Z"
    },
    {
      "leadId": "csv-door-30",
      "repName": "Harvey Shoemaker",
      "status": "No Answer",
      "isCA": false,
      "date": "2026-06-02",
      "address": "",
      "eventType": "csv_export_import",
      "ts": "2026-06-02T00:00:00Z"
    },
    {
      "leadId": "csv-door-31",
      "repName": "Harvey Shoemaker",
      "status": "No Answer",
      "isCA": false,
      "date": "2026-06-02",
      "address": "",
      "eventType": "csv_export_import",
      "ts": "2026-06-02T00:00:00Z"
    },
    {
      "leadId": "csv-door-32",
      "repName": "Harvey Shoemaker",
      "status": "No Answer",
      "isCA": false,
      "date": "2026-06-02",
      "address": "",
      "eventType": "csv_export_import",
      "ts": "2026-06-02T00:00:00Z"
    },
    {
      "leadId": "csv-door-33",
      "repName": "Harvey Shoemaker",
      "status": "No Answer",
      "isCA": false,
      "date": "2026-06-02",
      "address": "",
      "eventType": "csv_export_import",
      "ts": "2026-06-02T00:00:00Z"
    },
    {
      "leadId": "csv-door-34",
      "repName": "Harvey Shoemaker",
      "status": "No Answer",
      "isCA": false,
      "date": "2026-06-02",
      "address": "",
      "eventType": "csv_export_import",
      "ts": "2026-06-02T00:00:00Z"
    },
    {
      "leadId": "csv-door-35",
      "repName": "Harvey Shoemaker",
      "status": "No Answer",
      "isCA": false,
      "date": "2026-06-02",
      "address": "",
      "eventType": "csv_export_import",
      "ts": "2026-06-02T00:00:00Z"
    },
    {
      "leadId": "csv-door-36",
      "repName": "Harvey Shoemaker",
      "status": "No Answer",
      "isCA": false,
      "date": "2026-06-02",
      "address": "",
      "eventType": "csv_export_import",
      "ts": "2026-06-02T00:00:00Z"
    },
    {
      "leadId": "csv-door-37",
      "repName": "Harvey Shoemaker",
      "status": "No Answer",
      "isCA": false,
      "date": "2026-06-02",
      "address": "",
      "eventType": "csv_export_import",
      "ts": "2026-06-02T00:00:00Z"
    },
    {
      "leadId": "csv-door-38",
      "repName": "Harvey Shoemaker",
      "status": "No Answer",
      "isCA": false,
      "date": "2026-06-02",
      "address": "",
      "eventType": "csv_export_import",
      "ts": "2026-06-02T00:00:00Z"
    },
    {
      "leadId": "csv-door-39",
      "repName": "Harvey Shoemaker",
      "status": "No Answer",
      "isCA": false,
      "date": "2026-06-02",
      "address": "",
      "eventType": "csv_export_import",
      "ts": "2026-06-02T00:00:00Z"
    },
    {
      "leadId": "csv-door-40",
      "repName": "Harvey Shoemaker",
      "status": "No Answer",
      "isCA": false,
      "date": "2026-06-02",
      "address": "",
      "eventType": "csv_export_import",
      "ts": "2026-06-02T00:00:00Z"
    },
    {
      "leadId": "csv-door-41",
      "repName": "Harvey Shoemaker",
      "status": "No Answer",
      "isCA": false,
      "date": "2026-06-02",
      "address": "",
      "eventType": "csv_export_import",
      "ts": "2026-06-02T00:00:00Z"
    },
    {
      "leadId": "csv-door-42",
      "repName": "Harvey Shoemaker",
      "status": "No Answer",
      "isCA": false,
      "date": "2026-06-02",
      "address": "",
      "eventType": "csv_export_import",
      "ts": "2026-06-02T00:00:00Z"
    },
    {
      "leadId": "csv-door-43",
      "repName": "Harvey Shoemaker",
      "status": "No Answer",
      "isCA": false,
      "date": "2026-06-02",
      "address": "",
      "eventType": "csv_export_import",
      "ts": "2026-06-02T00:00:00Z"
    },
    {
      "leadId": "csv-door-44",
      "repName": "Harvey Shoemaker",
      "status": "No Answer",
      "isCA": false,
      "date": "2026-06-02",
      "address": "",
      "eventType": "csv_export_import",
      "ts": "2026-06-02T00:00:00Z"
    },
    {
      "leadId": "csv-door-45",
      "repName": "Harvey Shoemaker",
      "status": "No Answer",
      "isCA": false,
      "date": "2026-06-02",
      "address": "",
      "eventType": "csv_export_import",
      "ts": "2026-06-02T00:00:00Z"
    },
    {
      "leadId": "csv-door-46",
      "repName": "Harvey Shoemaker",
      "status": "No Answer",
      "isCA": false,
      "date": "2026-06-02",
      "address": "",
      "eventType": "csv_export_import",
      "ts": "2026-06-02T00:00:00Z"
    },
    {
      "leadId": "csv-door-47",
      "repName": "Harvey Shoemaker",
      "status": "No Answer",
      "isCA": false,
      "date": "2026-06-02",
      "address": "",
      "eventType": "csv_export_import",
      "ts": "2026-06-02T00:00:00Z"
    },
    {
      "leadId": "csv-door-48",
      "repName": "Harvey Shoemaker",
      "status": "No Answer",
      "isCA": false,
      "date": "2026-06-02",
      "address": "",
      "eventType": "csv_export_import",
      "ts": "2026-06-02T00:00:00Z"
    },
    {
      "leadId": "csv-door-49",
      "repName": "Harvey Shoemaker",
      "status": "No Answer",
      "isCA": false,
      "date": "2026-06-02",
      "address": "",
      "eventType": "csv_export_import",
      "ts": "2026-06-02T00:00:00Z"
    },
    {
      "leadId": "csv-door-50",
      "repName": "Harvey Shoemaker",
      "status": "No Answer",
      "isCA": false,
      "date": "2026-06-02",
      "address": "",
      "eventType": "csv_export_import",
      "ts": "2026-06-02T00:00:00Z"
    },
    {
      "leadId": "csv-door-51",
      "repName": "Harvey Shoemaker",
      "status": "No Answer",
      "isCA": false,
      "date": "2026-06-02",
      "address": "",
      "eventType": "csv_export_import",
      "ts": "2026-06-02T00:00:00Z"
    },
    {
      "leadId": "csv-door-52",
      "repName": "Harvey Shoemaker",
      "status": "No Answer",
      "isCA": false,
      "date": "2026-06-02",
      "address": "",
      "eventType": "csv_export_import",
      "ts": "2026-06-02T00:00:00Z"
    },
    {
      "leadId": "csv-door-53",
      "repName": "Harvey Shoemaker",
      "status": "No Answer",
      "isCA": false,
      "date": "2026-06-02",
      "address": "",
      "eventType": "csv_export_import",
      "ts": "2026-06-02T00:00:00Z"
    },
    {
      "leadId": "csv-door-54",
      "repName": "Harvey Shoemaker",
      "status": "No Answer",
      "isCA": false,
      "date": "2026-06-02",
      "address": "",
      "eventType": "csv_export_import",
      "ts": "2026-06-02T00:00:00Z"
    },
    {
      "leadId": "csv-door-55",
      "repName": "Harvey Shoemaker",
      "status": "No Answer",
      "isCA": false,
      "date": "2026-06-02",
      "address": "",
      "eventType": "csv_export_import",
      "ts": "2026-06-02T00:00:00Z"
    },
    {
      "leadId": "csv-door-56",
      "repName": "Harvey Shoemaker",
      "status": "No Answer",
      "isCA": false,
      "date": "2026-06-02",
      "address": "",
      "eventType": "csv_export_import",
      "ts": "2026-06-02T00:00:00Z"
    },
    {
      "leadId": "csv-door-57",
      "repName": "Harvey Shoemaker",
      "status": "No Answer",
      "isCA": false,
      "date": "2026-06-02",
      "address": "",
      "eventType": "csv_export_import",
      "ts": "2026-06-02T00:00:00Z"
    },
    {
      "leadId": "csv-door-58",
      "repName": "Harvey Shoemaker",
      "status": "No Answer",
      "isCA": false,
      "date": "2026-06-02",
      "address": "",
      "eventType": "csv_export_import",
      "ts": "2026-06-02T00:00:00Z"
    },
    {
      "leadId": "csv-door-59",
      "repName": "Harvey Shoemaker",
      "status": "No Answer",
      "isCA": false,
      "date": "2026-06-02",
      "address": "",
      "eventType": "csv_export_import",
      "ts": "2026-06-02T00:00:00Z"
    },
    {
      "leadId": "csv-door-60",
      "repName": "Harvey Shoemaker",
      "status": "No Answer",
      "isCA": false,
      "date": "2026-06-02",
      "address": "",
      "eventType": "csv_export_import",
      "ts": "2026-06-02T00:00:00Z"
    },
    {
      "leadId": "csv-door-61",
      "repName": "Harvey Shoemaker",
      "status": "No Answer",
      "isCA": false,
      "date": "2026-06-02",
      "address": "",
      "eventType": "csv_export_import",
      "ts": "2026-06-02T00:00:00Z"
    },
    {
      "leadId": "csv-door-62",
      "repName": "Harvey Shoemaker",
      "status": "No Answer",
      "isCA": false,
      "date": "2026-06-02",
      "address": "",
      "eventType": "csv_export_import",
      "ts": "2026-06-02T00:00:00Z"
    },
    {
      "leadId": "csv-door-63",
      "repName": "Harvey Shoemaker",
      "status": "No Answer",
      "isCA": false,
      "date": "2026-06-02",
      "address": "",
      "eventType": "csv_export_import",
      "ts": "2026-06-02T00:00:00Z"
    },
    {
      "leadId": "csv-door-64",
      "repName": "Harvey Shoemaker",
      "status": "No Answer",
      "isCA": false,
      "date": "2026-06-02",
      "address": "",
      "eventType": "csv_export_import",
      "ts": "2026-06-02T00:00:00Z"
    },
    {
      "leadId": "csv-door-65",
      "repName": "Harvey Shoemaker",
      "status": "No Answer",
      "isCA": false,
      "date": "2026-06-02",
      "address": "",
      "eventType": "csv_export_import",
      "ts": "2026-06-02T00:00:00Z"
    },
    {
      "leadId": "csv-door-66",
      "repName": "Harvey Shoemaker",
      "status": "No Answer",
      "isCA": false,
      "date": "2026-06-02",
      "address": "",
      "eventType": "csv_export_import",
      "ts": "2026-06-02T00:00:00Z"
    },
    {
      "leadId": "csv-door-67",
      "repName": "Harvey Shoemaker",
      "status": "No Answer",
      "isCA": false,
      "date": "2026-06-02",
      "address": "",
      "eventType": "csv_export_import",
      "ts": "2026-06-02T00:00:00Z"
    },
    {
      "leadId": "csv-door-68",
      "repName": "Harvey Shoemaker",
      "status": "No Answer",
      "isCA": false,
      "date": "2026-06-02",
      "address": "",
      "eventType": "csv_export_import",
      "ts": "2026-06-02T00:00:00Z"
    },
    {
      "leadId": "csv-door-69",
      "repName": "Harvey Shoemaker",
      "status": "No Answer",
      "isCA": false,
      "date": "2026-06-02",
      "address": "",
      "eventType": "csv_export_import",
      "ts": "2026-06-02T00:00:00Z"
    },
    {
      "leadId": "csv-door-70",
      "repName": "Harvey Shoemaker",
      "status": "No Answer",
      "isCA": false,
      "date": "2026-06-02",
      "address": "",
      "eventType": "csv_export_import",
      "ts": "2026-06-02T00:00:00Z"
    },
    {
      "leadId": "csv-door-71",
      "repName": "Harvey Shoemaker",
      "status": "No Answer",
      "isCA": false,
      "date": "2026-06-02",
      "address": "",
      "eventType": "csv_export_import",
      "ts": "2026-06-02T00:00:00Z"
    },
    {
      "leadId": "csv-door-72",
      "repName": "Harvey Shoemaker",
      "status": "No Answer",
      "isCA": false,
      "date": "2026-06-02",
      "address": "",
      "eventType": "csv_export_import",
      "ts": "2026-06-02T00:00:00Z"
    },
    {
      "leadId": "csv-door-73",
      "repName": "Andrew Funk",
      "status": "No Answer",
      "isCA": false,
      "date": "2026-06-02",
      "address": "",
      "eventType": "csv_export_import",
      "ts": "2026-06-02T00:00:00Z"
    },
    {
      "leadId": "csv-door-74",
      "repName": "Andrew Funk",
      "status": "No Answer",
      "isCA": false,
      "date": "2026-06-02",
      "address": "",
      "eventType": "csv_export_import",
      "ts": "2026-06-02T00:00:00Z"
    },
    {
      "leadId": "csv-door-75",
      "repName": "Andrew Funk",
      "status": "No Answer",
      "isCA": false,
      "date": "2026-06-02",
      "address": "",
      "eventType": "csv_export_import",
      "ts": "2026-06-02T00:00:00Z"
    },
    {
      "leadId": "csv-door-76",
      "repName": "Andrew Funk",
      "status": "No Answer",
      "isCA": false,
      "date": "2026-06-02",
      "address": "",
      "eventType": "csv_export_import",
      "ts": "2026-06-02T00:00:00Z"
    },
    {
      "leadId": "csv-door-77",
      "repName": "Andrew Funk",
      "status": "No Answer",
      "isCA": false,
      "date": "2026-06-02",
      "address": "",
      "eventType": "csv_export_import",
      "ts": "2026-06-02T00:00:00Z"
    },
    {
      "leadId": "csv-door-78",
      "repName": "Andrew Funk",
      "status": "No Answer",
      "isCA": false,
      "date": "2026-06-02",
      "address": "",
      "eventType": "csv_export_import",
      "ts": "2026-06-02T00:00:00Z"
    },
    {
      "leadId": "csv-door-79",
      "repName": "Andrew Funk",
      "status": "No Answer",
      "isCA": false,
      "date": "2026-06-02",
      "address": "",
      "eventType": "csv_export_import",
      "ts": "2026-06-02T00:00:00Z"
    },
    {
      "leadId": "csv-door-80",
      "repName": "Andrew Funk",
      "status": "No Answer",
      "isCA": false,
      "date": "2026-06-02",
      "address": "",
      "eventType": "csv_export_import",
      "ts": "2026-06-02T00:00:00Z"
    },
    {
      "leadId": "csv-door-81",
      "repName": "Andrew Funk",
      "status": "No Answer",
      "isCA": false,
      "date": "2026-06-02",
      "address": "",
      "eventType": "csv_export_import",
      "ts": "2026-06-02T00:00:00Z"
    },
    {
      "leadId": "csv-door-82",
      "repName": "Andrew Funk",
      "status": "No Answer",
      "isCA": false,
      "date": "2026-06-02",
      "address": "",
      "eventType": "csv_export_import",
      "ts": "2026-06-02T00:00:00Z"
    },
    {
      "leadId": "csv-door-83",
      "repName": "Andrew Funk",
      "status": "No Answer",
      "isCA": false,
      "date": "2026-06-02",
      "address": "",
      "eventType": "csv_export_import",
      "ts": "2026-06-02T00:00:00Z"
    },
    {
      "leadId": "csv-door-84",
      "repName": "Andrew Funk",
      "status": "No Answer",
      "isCA": false,
      "date": "2026-06-02",
      "address": "",
      "eventType": "csv_export_import",
      "ts": "2026-06-02T00:00:00Z"
    },
    {
      "leadId": "csv-door-85",
      "repName": "Andrew Funk",
      "status": "No Answer",
      "isCA": false,
      "date": "2026-06-02",
      "address": "",
      "eventType": "csv_export_import",
      "ts": "2026-06-02T00:00:00Z"
    },
    {
      "leadId": "csv-door-86",
      "repName": "Andrew Funk",
      "status": "No Answer",
      "isCA": false,
      "date": "2026-06-02",
      "address": "",
      "eventType": "csv_export_import",
      "ts": "2026-06-02T00:00:00Z"
    },
    {
      "leadId": "csv-door-87",
      "repName": "Andrew Funk",
      "status": "No Answer",
      "isCA": false,
      "date": "2026-06-02",
      "address": "",
      "eventType": "csv_export_import",
      "ts": "2026-06-02T00:00:00Z"
    },
    {
      "leadId": "csv-door-88",
      "repName": "Andrew Funk",
      "status": "No Answer",
      "isCA": false,
      "date": "2026-06-02",
      "address": "",
      "eventType": "csv_export_import",
      "ts": "2026-06-02T00:00:00Z"
    },
    {
      "leadId": "csv-door-89",
      "repName": "Andrew Funk",
      "status": "No Answer",
      "isCA": false,
      "date": "2026-06-02",
      "address": "",
      "eventType": "csv_export_import",
      "ts": "2026-06-02T00:00:00Z"
    },
    {
      "leadId": "csv-door-90",
      "repName": "Andrew Funk",
      "status": "No Answer",
      "isCA": false,
      "date": "2026-06-02",
      "address": "",
      "eventType": "csv_export_import",
      "ts": "2026-06-02T00:00:00Z"
    },
    {
      "leadId": "csv-door-91",
      "repName": "Andrew Funk",
      "status": "No Answer",
      "isCA": false,
      "date": "2026-06-02",
      "address": "",
      "eventType": "csv_export_import",
      "ts": "2026-06-02T00:00:00Z"
    },
    {
      "leadId": "csv-door-92",
      "repName": "Andrew Funk",
      "status": "No Answer",
      "isCA": false,
      "date": "2026-06-02",
      "address": "",
      "eventType": "csv_export_import",
      "ts": "2026-06-02T00:00:00Z"
    },
    {
      "leadId": "csv-door-93",
      "repName": "Andrew Funk",
      "status": "No Answer",
      "isCA": false,
      "date": "2026-06-02",
      "address": "",
      "eventType": "csv_export_import",
      "ts": "2026-06-02T00:00:00Z"
    },
    {
      "leadId": "csv-door-94",
      "repName": "Andrew Funk",
      "status": "No Answer",
      "isCA": false,
      "date": "2026-06-02",
      "address": "",
      "eventType": "csv_export_import",
      "ts": "2026-06-02T00:00:00Z"
    },
    {
      "leadId": "csv-door-95",
      "repName": "Andrew Funk",
      "status": "No Answer",
      "isCA": false,
      "date": "2026-06-02",
      "address": "",
      "eventType": "csv_export_import",
      "ts": "2026-06-02T00:00:00Z"
    },
    {
      "leadId": "csv-door-96",
      "repName": "Andrew Funk",
      "status": "No Answer",
      "isCA": false,
      "date": "2026-06-02",
      "address": "",
      "eventType": "csv_export_import",
      "ts": "2026-06-02T00:00:00Z"
    },
    {
      "leadId": "csv-door-97",
      "repName": "Andrew Funk",
      "status": "No Answer",
      "isCA": false,
      "date": "2026-06-02",
      "address": "",
      "eventType": "csv_export_import",
      "ts": "2026-06-02T00:00:00Z"
    },
    {
      "leadId": "csv-door-98",
      "repName": "Andrew Funk",
      "status": "No Answer",
      "isCA": false,
      "date": "2026-06-02",
      "address": "",
      "eventType": "csv_export_import",
      "ts": "2026-06-02T00:00:00Z"
    },
    {
      "leadId": "csv-door-99",
      "repName": "Andrew Funk",
      "status": "No Answer",
      "isCA": false,
      "date": "2026-06-02",
      "address": "",
      "eventType": "csv_export_import",
      "ts": "2026-06-02T00:00:00Z"
    },
    {
      "leadId": "csv-door-100",
      "repName": "Andrew Funk",
      "status": "No Answer",
      "isCA": false,
      "date": "2026-06-02",
      "address": "",
      "eventType": "csv_export_import",
      "ts": "2026-06-02T00:00:00Z"
    },
    {
      "leadId": "csv-door-101",
      "repName": "Andrew Funk",
      "status": "No Answer",
      "isCA": false,
      "date": "2026-06-02",
      "address": "",
      "eventType": "csv_export_import",
      "ts": "2026-06-02T00:00:00Z"
    },
    {
      "leadId": "csv-door-102",
      "repName": "Andrew Funk",
      "status": "No Answer",
      "isCA": false,
      "date": "2026-06-02",
      "address": "",
      "eventType": "csv_export_import",
      "ts": "2026-06-02T00:00:00Z"
    },
    {
      "leadId": "csv-door-103",
      "repName": "Andrew Funk",
      "status": "No Answer",
      "isCA": false,
      "date": "2026-06-02",
      "address": "",
      "eventType": "csv_export_import",
      "ts": "2026-06-02T00:00:00Z"
    },
    {
      "leadId": "csv-door-104",
      "repName": "Andrew Funk",
      "status": "No Answer",
      "isCA": false,
      "date": "2026-06-02",
      "address": "",
      "eventType": "csv_export_import",
      "ts": "2026-06-02T00:00:00Z"
    },
    {
      "leadId": "csv-door-105",
      "repName": "Andrew Funk",
      "status": "No Answer",
      "isCA": false,
      "date": "2026-06-02",
      "address": "",
      "eventType": "csv_export_import",
      "ts": "2026-06-02T00:00:00Z"
    },
    {
      "leadId": "csv-door-106",
      "repName": "Andrew Funk",
      "status": "No Answer",
      "isCA": false,
      "date": "2026-06-02",
      "address": "",
      "eventType": "csv_export_import",
      "ts": "2026-06-02T00:00:00Z"
    },
    {
      "leadId": "csv-door-107",
      "repName": "Andrew Funk",
      "status": "No Answer",
      "isCA": false,
      "date": "2026-06-02",
      "address": "",
      "eventType": "csv_export_import",
      "ts": "2026-06-02T00:00:00Z"
    },
    {
      "leadId": "csv-door-108",
      "repName": "Andrew Funk",
      "status": "No Answer",
      "isCA": false,
      "date": "2026-06-02",
      "address": "",
      "eventType": "csv_export_import",
      "ts": "2026-06-02T00:00:00Z"
    },
    {
      "leadId": "csv-door-109",
      "repName": "Andrew Funk",
      "status": "No Answer",
      "isCA": false,
      "date": "2026-06-02",
      "address": "",
      "eventType": "csv_export_import",
      "ts": "2026-06-02T00:00:00Z"
    },
    {
      "leadId": "csv-door-110",
      "repName": "Andrew Funk",
      "status": "No Answer",
      "isCA": false,
      "date": "2026-06-02",
      "address": "",
      "eventType": "csv_export_import",
      "ts": "2026-06-02T00:00:00Z"
    },
    {
      "leadId": "csv-door-111",
      "repName": "Andrew Funk",
      "status": "No Answer",
      "isCA": false,
      "date": "2026-06-02",
      "address": "",
      "eventType": "csv_export_import",
      "ts": "2026-06-02T00:00:00Z"
    },
    {
      "leadId": "csv-door-112",
      "repName": "Andrew Funk",
      "status": "No Answer",
      "isCA": false,
      "date": "2026-06-02",
      "address": "",
      "eventType": "csv_export_import",
      "ts": "2026-06-02T00:00:00Z"
    },
    {
      "leadId": "csv-door-113",
      "repName": "Andrew Funk",
      "status": "No Answer",
      "isCA": false,
      "date": "2026-06-02",
      "address": "",
      "eventType": "csv_export_import",
      "ts": "2026-06-02T00:00:00Z"
    },
    {
      "leadId": "csv-door-114",
      "repName": "Andrew Funk",
      "status": "No Answer",
      "isCA": false,
      "date": "2026-06-02",
      "address": "",
      "eventType": "csv_export_import",
      "ts": "2026-06-02T00:00:00Z"
    },
    {
      "leadId": "csv-door-115",
      "repName": "Andrew Funk",
      "status": "No Answer",
      "isCA": false,
      "date": "2026-06-02",
      "address": "",
      "eventType": "csv_export_import",
      "ts": "2026-06-02T00:00:00Z"
    },
    {
      "leadId": "csv-door-116",
      "repName": "Andrew Funk",
      "status": "No Answer",
      "isCA": false,
      "date": "2026-06-02",
      "address": "",
      "eventType": "csv_export_import",
      "ts": "2026-06-02T00:00:00Z"
    },
    {
      "leadId": "csv-door-117",
      "repName": "Andrew Funk",
      "status": "No Answer",
      "isCA": false,
      "date": "2026-06-02",
      "address": "",
      "eventType": "csv_export_import",
      "ts": "2026-06-02T00:00:00Z"
    },
    {
      "leadId": "csv-door-118",
      "repName": "Andrew Funk",
      "status": "No Answer",
      "isCA": false,
      "date": "2026-06-02",
      "address": "",
      "eventType": "csv_export_import",
      "ts": "2026-06-02T00:00:00Z"
    },
    {
      "leadId": "csv-door-119",
      "repName": "Andrew Funk",
      "status": "No Answer",
      "isCA": false,
      "date": "2026-06-02",
      "address": "",
      "eventType": "csv_export_import",
      "ts": "2026-06-02T00:00:00Z"
    },
    {
      "leadId": "csv-door-120",
      "repName": "Andrew Funk",
      "status": "No Answer",
      "isCA": false,
      "date": "2026-06-02",
      "address": "",
      "eventType": "csv_export_import",
      "ts": "2026-06-02T00:00:00Z"
    },
    {
      "leadId": "csv-door-121",
      "repName": "Andrew Funk",
      "status": "No Answer",
      "isCA": false,
      "date": "2026-06-02",
      "address": "",
      "eventType": "csv_export_import",
      "ts": "2026-06-02T00:00:00Z"
    },
    {
      "leadId": "csv-door-122",
      "repName": "Andrew Funk",
      "status": "No Answer",
      "isCA": false,
      "date": "2026-06-02",
      "address": "",
      "eventType": "csv_export_import",
      "ts": "2026-06-02T00:00:00Z"
    },
    {
      "leadId": "csv-door-123",
      "repName": "Andrew Funk",
      "status": "No Answer",
      "isCA": false,
      "date": "2026-06-02",
      "address": "",
      "eventType": "csv_export_import",
      "ts": "2026-06-02T00:00:00Z"
    },
    {
      "leadId": "csv-door-124",
      "repName": "Andrew Funk",
      "status": "No Answer",
      "isCA": false,
      "date": "2026-06-02",
      "address": "",
      "eventType": "csv_export_import",
      "ts": "2026-06-02T00:00:00Z"
    },
    {
      "leadId": "csv-door-125",
      "repName": "David Kerns",
      "status": "No Answer",
      "isCA": false,
      "date": "2026-06-02",
      "address": "",
      "eventType": "csv_export_import",
      "ts": "2026-06-02T00:00:00Z"
    },
    {
      "leadId": "csv-door-126",
      "repName": "David Kerns",
      "status": "No Answer",
      "isCA": false,
      "date": "2026-06-02",
      "address": "",
      "eventType": "csv_export_import",
      "ts": "2026-06-02T00:00:00Z"
    },
    {
      "leadId": "csv-door-127",
      "repName": "David Kerns",
      "status": "No Answer",
      "isCA": false,
      "date": "2026-06-02",
      "address": "",
      "eventType": "csv_export_import",
      "ts": "2026-06-02T00:00:00Z"
    },
    {
      "leadId": "csv-door-128",
      "repName": "David Kerns",
      "status": "No Answer",
      "isCA": false,
      "date": "2026-06-02",
      "address": "",
      "eventType": "csv_export_import",
      "ts": "2026-06-02T00:00:00Z"
    },
    {
      "leadId": "csv-door-129",
      "repName": "David Kerns",
      "status": "No Answer",
      "isCA": false,
      "date": "2026-06-02",
      "address": "",
      "eventType": "csv_export_import",
      "ts": "2026-06-02T00:00:00Z"
    },
    {
      "leadId": "csv-door-130",
      "repName": "David Kerns",
      "status": "No Answer",
      "isCA": false,
      "date": "2026-06-02",
      "address": "",
      "eventType": "csv_export_import",
      "ts": "2026-06-02T00:00:00Z"
    },
    {
      "leadId": "csv-door-131",
      "repName": "David Kerns",
      "status": "No Answer",
      "isCA": false,
      "date": "2026-06-02",
      "address": "",
      "eventType": "csv_export_import",
      "ts": "2026-06-02T00:00:00Z"
    },
    {
      "leadId": "csv-door-132",
      "repName": "David Kerns",
      "status": "No Answer",
      "isCA": false,
      "date": "2026-06-02",
      "address": "",
      "eventType": "csv_export_import",
      "ts": "2026-06-02T00:00:00Z"
    },
    {
      "leadId": "csv-door-133",
      "repName": "David Kerns",
      "status": "No Answer",
      "isCA": false,
      "date": "2026-06-02",
      "address": "",
      "eventType": "csv_export_import",
      "ts": "2026-06-02T00:00:00Z"
    },
    {
      "leadId": "csv-door-134",
      "repName": "David Kerns",
      "status": "No Answer",
      "isCA": false,
      "date": "2026-06-02",
      "address": "",
      "eventType": "csv_export_import",
      "ts": "2026-06-02T00:00:00Z"
    },
    {
      "leadId": "csv-door-135",
      "repName": "David Kerns",
      "status": "No Answer",
      "isCA": false,
      "date": "2026-06-02",
      "address": "",
      "eventType": "csv_export_import",
      "ts": "2026-06-02T00:00:00Z"
    },
    {
      "leadId": "csv-door-136",
      "repName": "David Kerns",
      "status": "No Answer",
      "isCA": false,
      "date": "2026-06-02",
      "address": "",
      "eventType": "csv_export_import",
      "ts": "2026-06-02T00:00:00Z"
    },
    {
      "leadId": "csv-door-137",
      "repName": "David Kerns",
      "status": "No Answer",
      "isCA": false,
      "date": "2026-06-02",
      "address": "",
      "eventType": "csv_export_import",
      "ts": "2026-06-02T00:00:00Z"
    },
    {
      "leadId": "csv-door-138",
      "repName": "David Kerns",
      "status": "No Answer",
      "isCA": false,
      "date": "2026-06-02",
      "address": "",
      "eventType": "csv_export_import",
      "ts": "2026-06-02T00:00:00Z"
    },
    {
      "leadId": "csv-door-139",
      "repName": "David Kerns",
      "status": "No Answer",
      "isCA": false,
      "date": "2026-06-02",
      "address": "",
      "eventType": "csv_export_import",
      "ts": "2026-06-02T00:00:00Z"
    },
    {
      "leadId": "csv-door-140",
      "repName": "David Kerns",
      "status": "No Answer",
      "isCA": false,
      "date": "2026-06-02",
      "address": "",
      "eventType": "csv_export_import",
      "ts": "2026-06-02T00:00:00Z"
    },
    {
      "leadId": "csv-door-141",
      "repName": "David Kerns",
      "status": "No Answer",
      "isCA": false,
      "date": "2026-06-02",
      "address": "",
      "eventType": "csv_export_import",
      "ts": "2026-06-02T00:00:00Z"
    },
    {
      "leadId": "csv-door-142",
      "repName": "David Kerns",
      "status": "No Answer",
      "isCA": false,
      "date": "2026-06-02",
      "address": "",
      "eventType": "csv_export_import",
      "ts": "2026-06-02T00:00:00Z"
    },
    {
      "leadId": "csv-door-143",
      "repName": "David Kerns",
      "status": "No Answer",
      "isCA": false,
      "date": "2026-06-02",
      "address": "",
      "eventType": "csv_export_import",
      "ts": "2026-06-02T00:00:00Z"
    },
    {
      "leadId": "csv-door-144",
      "repName": "David Kerns",
      "status": "No Answer",
      "isCA": false,
      "date": "2026-06-02",
      "address": "",
      "eventType": "csv_export_import",
      "ts": "2026-06-02T00:00:00Z"
    },
    {
      "leadId": "csv-door-145",
      "repName": "David Kerns",
      "status": "No Answer",
      "isCA": false,
      "date": "2026-06-02",
      "address": "",
      "eventType": "csv_export_import",
      "ts": "2026-06-02T00:00:00Z"
    },
    {
      "leadId": "csv-door-146",
      "repName": "David Kerns",
      "status": "No Answer",
      "isCA": false,
      "date": "2026-06-02",
      "address": "",
      "eventType": "csv_export_import",
      "ts": "2026-06-02T00:00:00Z"
    },
    {
      "leadId": "csv-door-147",
      "repName": "David Kerns",
      "status": "No Answer",
      "isCA": false,
      "date": "2026-06-02",
      "address": "",
      "eventType": "csv_export_import",
      "ts": "2026-06-02T00:00:00Z"
    },
    {
      "leadId": "csv-door-148",
      "repName": "David Kerns",
      "status": "No Answer",
      "isCA": false,
      "date": "2026-06-02",
      "address": "",
      "eventType": "csv_export_import",
      "ts": "2026-06-02T00:00:00Z"
    },
    {
      "leadId": "csv-door-149",
      "repName": "David Kerns",
      "status": "No Answer",
      "isCA": false,
      "date": "2026-06-02",
      "address": "",
      "eventType": "csv_export_import",
      "ts": "2026-06-02T00:00:00Z"
    },
    {
      "leadId": "csv-door-150",
      "repName": "David Kerns",
      "status": "No Answer",
      "isCA": false,
      "date": "2026-06-02",
      "address": "",
      "eventType": "csv_export_import",
      "ts": "2026-06-02T00:00:00Z"
    },
    {
      "leadId": "csv-door-151",
      "repName": "David Kerns",
      "status": "No Answer",
      "isCA": false,
      "date": "2026-06-02",
      "address": "",
      "eventType": "csv_export_import",
      "ts": "2026-06-02T00:00:00Z"
    },
    {
      "leadId": "csv-door-152",
      "repName": "David Kerns",
      "status": "No Answer",
      "isCA": false,
      "date": "2026-06-02",
      "address": "",
      "eventType": "csv_export_import",
      "ts": "2026-06-02T00:00:00Z"
    },
    {
      "leadId": "csv-door-153",
      "repName": "David Kerns",
      "status": "No Answer",
      "isCA": false,
      "date": "2026-06-02",
      "address": "",
      "eventType": "csv_export_import",
      "ts": "2026-06-02T00:00:00Z"
    },
    {
      "leadId": "csv-door-154",
      "repName": "David Kerns",
      "status": "No Answer",
      "isCA": false,
      "date": "2026-06-02",
      "address": "",
      "eventType": "csv_export_import",
      "ts": "2026-06-02T00:00:00Z"
    },
    {
      "leadId": "csv-door-155",
      "repName": "David Kerns",
      "status": "No Answer",
      "isCA": false,
      "date": "2026-06-02",
      "address": "",
      "eventType": "csv_export_import",
      "ts": "2026-06-02T00:00:00Z"
    },
    {
      "leadId": "csv-door-156",
      "repName": "David Kerns",
      "status": "No Answer",
      "isCA": false,
      "date": "2026-06-02",
      "address": "",
      "eventType": "csv_export_import",
      "ts": "2026-06-02T00:00:00Z"
    },
    {
      "leadId": "csv-door-157",
      "repName": "David Kerns",
      "status": "No Answer",
      "isCA": false,
      "date": "2026-06-02",
      "address": "",
      "eventType": "csv_export_import",
      "ts": "2026-06-02T00:00:00Z"
    },
    {
      "leadId": "csv-door-158",
      "repName": "David Kerns",
      "status": "No Answer",
      "isCA": false,
      "date": "2026-06-02",
      "address": "",
      "eventType": "csv_export_import",
      "ts": "2026-06-02T00:00:00Z"
    },
    {
      "leadId": "csv-door-159",
      "repName": "David Kerns",
      "status": "No Answer",
      "isCA": false,
      "date": "2026-06-02",
      "address": "",
      "eventType": "csv_export_import",
      "ts": "2026-06-02T00:00:00Z"
    },
    {
      "leadId": "csv-door-160",
      "repName": "David Kerns",
      "status": "No Answer",
      "isCA": false,
      "date": "2026-06-02",
      "address": "",
      "eventType": "csv_export_import",
      "ts": "2026-06-02T00:00:00Z"
    },
    {
      "leadId": "csv-door-161",
      "repName": "David Kerns",
      "status": "No Answer",
      "isCA": false,
      "date": "2026-06-02",
      "address": "",
      "eventType": "csv_export_import",
      "ts": "2026-06-02T00:00:00Z"
    },
    {
      "leadId": "csv-door-162",
      "repName": "David Kerns",
      "status": "No Answer",
      "isCA": false,
      "date": "2026-06-02",
      "address": "",
      "eventType": "csv_export_import",
      "ts": "2026-06-02T00:00:00Z"
    },
    {
      "leadId": "csv-door-163",
      "repName": "David Kerns",
      "status": "No Answer",
      "isCA": false,
      "date": "2026-06-02",
      "address": "",
      "eventType": "csv_export_import",
      "ts": "2026-06-02T00:00:00Z"
    },
    {
      "leadId": "csv-door-164",
      "repName": "Christian Brown",
      "status": "No Answer",
      "isCA": false,
      "date": "2026-06-02",
      "address": "",
      "eventType": "csv_export_import",
      "ts": "2026-06-02T00:00:00Z"
    },
    {
      "leadId": "csv-door-165",
      "repName": "Christian Brown",
      "status": "No Answer",
      "isCA": false,
      "date": "2026-06-02",
      "address": "",
      "eventType": "csv_export_import",
      "ts": "2026-06-02T00:00:00Z"
    },
    {
      "leadId": "csv-door-166",
      "repName": "Christian Brown",
      "status": "No Answer",
      "isCA": false,
      "date": "2026-06-02",
      "address": "",
      "eventType": "csv_export_import",
      "ts": "2026-06-02T00:00:00Z"
    },
    {
      "leadId": "csv-door-167",
      "repName": "Christian Brown",
      "status": "No Answer",
      "isCA": false,
      "date": "2026-06-02",
      "address": "",
      "eventType": "csv_export_import",
      "ts": "2026-06-02T00:00:00Z"
    },
    {
      "leadId": "csv-door-168",
      "repName": "Christian Brown",
      "status": "No Answer",
      "isCA": false,
      "date": "2026-06-02",
      "address": "",
      "eventType": "csv_export_import",
      "ts": "2026-06-02T00:00:00Z"
    },
    {
      "leadId": "csv-door-169",
      "repName": "Christian Brown",
      "status": "No Answer",
      "isCA": false,
      "date": "2026-06-02",
      "address": "",
      "eventType": "csv_export_import",
      "ts": "2026-06-02T00:00:00Z"
    },
    {
      "leadId": "csv-door-170",
      "repName": "Christian Brown",
      "status": "No Answer",
      "isCA": false,
      "date": "2026-06-02",
      "address": "",
      "eventType": "csv_export_import",
      "ts": "2026-06-02T00:00:00Z"
    },
    {
      "leadId": "csv-door-171",
      "repName": "Christian Brown",
      "status": "No Answer",
      "isCA": false,
      "date": "2026-06-02",
      "address": "",
      "eventType": "csv_export_import",
      "ts": "2026-06-02T00:00:00Z"
    },
    {
      "leadId": "csv-door-172",
      "repName": "Christian Brown",
      "status": "No Answer",
      "isCA": false,
      "date": "2026-06-02",
      "address": "",
      "eventType": "csv_export_import",
      "ts": "2026-06-02T00:00:00Z"
    },
    {
      "leadId": "csv-door-173",
      "repName": "Christian Brown",
      "status": "No Answer",
      "isCA": false,
      "date": "2026-06-02",
      "address": "",
      "eventType": "csv_export_import",
      "ts": "2026-06-02T00:00:00Z"
    },
    {
      "leadId": "csv-door-174",
      "repName": "Christian Brown",
      "status": "No Answer",
      "isCA": false,
      "date": "2026-06-02",
      "address": "",
      "eventType": "csv_export_import",
      "ts": "2026-06-02T00:00:00Z"
    },
    {
      "leadId": "csv-door-175",
      "repName": "Christian Brown",
      "status": "No Answer",
      "isCA": false,
      "date": "2026-06-02",
      "address": "",
      "eventType": "csv_export_import",
      "ts": "2026-06-02T00:00:00Z"
    },
    {
      "leadId": "csv-door-176",
      "repName": "Christian Brown",
      "status": "No Answer",
      "isCA": false,
      "date": "2026-06-02",
      "address": "",
      "eventType": "csv_export_import",
      "ts": "2026-06-02T00:00:00Z"
    },
    {
      "leadId": "csv-door-177",
      "repName": "Christian Brown",
      "status": "No Answer",
      "isCA": false,
      "date": "2026-06-02",
      "address": "",
      "eventType": "csv_export_import",
      "ts": "2026-06-02T00:00:00Z"
    },
    {
      "leadId": "csv-door-178",
      "repName": "Christian Brown",
      "status": "No Answer",
      "isCA": false,
      "date": "2026-06-02",
      "address": "",
      "eventType": "csv_export_import",
      "ts": "2026-06-02T00:00:00Z"
    },
    {
      "leadId": "csv-door-179",
      "repName": "Christian Brown",
      "status": "No Answer",
      "isCA": false,
      "date": "2026-06-02",
      "address": "",
      "eventType": "csv_export_import",
      "ts": "2026-06-02T00:00:00Z"
    },
    {
      "leadId": "csv-door-180",
      "repName": "Christian Brown",
      "status": "No Answer",
      "isCA": false,
      "date": "2026-06-02",
      "address": "",
      "eventType": "csv_export_import",
      "ts": "2026-06-02T00:00:00Z"
    },
    {
      "leadId": "csv-door-181",
      "repName": "Christian Brown",
      "status": "No Answer",
      "isCA": false,
      "date": "2026-06-02",
      "address": "",
      "eventType": "csv_export_import",
      "ts": "2026-06-02T00:00:00Z"
    },
    {
      "leadId": "csv-door-182",
      "repName": "Christian Brown",
      "status": "No Answer",
      "isCA": false,
      "date": "2026-06-02",
      "address": "",
      "eventType": "csv_export_import",
      "ts": "2026-06-02T00:00:00Z"
    },
    {
      "leadId": "csv-door-183",
      "repName": "Christian Brown",
      "status": "No Answer",
      "isCA": false,
      "date": "2026-06-02",
      "address": "",
      "eventType": "csv_export_import",
      "ts": "2026-06-02T00:00:00Z"
    },
    {
      "leadId": "csv-door-184",
      "repName": "Christian Brown",
      "status": "No Answer",
      "isCA": false,
      "date": "2026-06-02",
      "address": "",
      "eventType": "csv_export_import",
      "ts": "2026-06-02T00:00:00Z"
    },
    {
      "leadId": "csv-door-185",
      "repName": "Kelly Alston",
      "status": "No Answer",
      "isCA": false,
      "date": "2026-06-02",
      "address": "",
      "eventType": "csv_export_import",
      "ts": "2026-06-02T00:00:00Z"
    },
    {
      "leadId": "csv-door-186",
      "repName": "Kelly Alston",
      "status": "No Answer",
      "isCA": false,
      "date": "2026-06-02",
      "address": "",
      "eventType": "csv_export_import",
      "ts": "2026-06-02T00:00:00Z"
    },
    {
      "leadId": "csv-door-187",
      "repName": "Kelly Alston",
      "status": "No Answer",
      "isCA": false,
      "date": "2026-06-02",
      "address": "",
      "eventType": "csv_export_import",
      "ts": "2026-06-02T00:00:00Z"
    },
    {
      "leadId": "csv-door-188",
      "repName": "Kelly Alston",
      "status": "No Answer",
      "isCA": false,
      "date": "2026-06-02",
      "address": "",
      "eventType": "csv_export_import",
      "ts": "2026-06-02T00:00:00Z"
    },
    {
      "leadId": "csv-door-189",
      "repName": "Kelly Alston",
      "status": "No Answer",
      "isCA": false,
      "date": "2026-06-02",
      "address": "",
      "eventType": "csv_export_import",
      "ts": "2026-06-02T00:00:00Z"
    },
    {
      "leadId": "csv-door-190",
      "repName": "Kelly Alston",
      "status": "No Answer",
      "isCA": false,
      "date": "2026-06-02",
      "address": "",
      "eventType": "csv_export_import",
      "ts": "2026-06-02T00:00:00Z"
    },
    {
      "leadId": "csv-door-191",
      "repName": "Kelly Alston",
      "status": "No Answer",
      "isCA": false,
      "date": "2026-06-02",
      "address": "",
      "eventType": "csv_export_import",
      "ts": "2026-06-02T00:00:00Z"
    },
    {
      "leadId": "csv-door-192",
      "repName": "Kelly Alston",
      "status": "No Answer",
      "isCA": false,
      "date": "2026-06-02",
      "address": "",
      "eventType": "csv_export_import",
      "ts": "2026-06-02T00:00:00Z"
    },
    {
      "leadId": "csv-door-193",
      "repName": "Kelly Alston",
      "status": "No Answer",
      "isCA": false,
      "date": "2026-06-02",
      "address": "",
      "eventType": "csv_export_import",
      "ts": "2026-06-02T00:00:00Z"
    },
    {
      "leadId": "csv-door-194",
      "repName": "Kelly Alston",
      "status": "No Answer",
      "isCA": false,
      "date": "2026-06-02",
      "address": "",
      "eventType": "csv_export_import",
      "ts": "2026-06-02T00:00:00Z"
    },
    {
      "leadId": "csv-door-195",
      "repName": "Kelly Alston",
      "status": "No Answer",
      "isCA": false,
      "date": "2026-06-02",
      "address": "",
      "eventType": "csv_export_import",
      "ts": "2026-06-02T00:00:00Z"
    },
    {
      "leadId": "csv-door-196",
      "repName": "Kelly Alston",
      "status": "No Answer",
      "isCA": false,
      "date": "2026-06-02",
      "address": "",
      "eventType": "csv_export_import",
      "ts": "2026-06-02T00:00:00Z"
    },
    {
      "leadId": "csv-door-197",
      "repName": "Kelly Alston",
      "status": "No Answer",
      "isCA": false,
      "date": "2026-06-02",
      "address": "",
      "eventType": "csv_export_import",
      "ts": "2026-06-02T00:00:00Z"
    },
    {
      "leadId": "csv-door-198",
      "repName": "Kelly Alston",
      "status": "No Answer",
      "isCA": false,
      "date": "2026-06-02",
      "address": "",
      "eventType": "csv_export_import",
      "ts": "2026-06-02T00:00:00Z"
    },
    {
      "leadId": "csv-door-199",
      "repName": "Kelly Alston",
      "status": "No Answer",
      "isCA": false,
      "date": "2026-06-02",
      "address": "",
      "eventType": "csv_export_import",
      "ts": "2026-06-02T00:00:00Z"
    },
    {
      "leadId": "csv-door-200",
      "repName": "Kelly Alston",
      "status": "No Answer",
      "isCA": false,
      "date": "2026-06-02",
      "address": "",
      "eventType": "csv_export_import",
      "ts": "2026-06-02T00:00:00Z"
    },
    {
      "leadId": "csv-door-201",
      "repName": "Michael McCarthy",
      "status": "No Answer",
      "isCA": false,
      "date": "2026-06-02",
      "address": "",
      "eventType": "csv_export_import",
      "ts": "2026-06-02T00:00:00Z"
    },
    {
      "leadId": "csv-door-202",
      "repName": "Michael McCarthy",
      "status": "No Answer",
      "isCA": false,
      "date": "2026-06-02",
      "address": "",
      "eventType": "csv_export_import",
      "ts": "2026-06-02T00:00:00Z"
    },
    {
      "leadId": "csv-door-203",
      "repName": "Michael McCarthy",
      "status": "No Answer",
      "isCA": false,
      "date": "2026-06-02",
      "address": "",
      "eventType": "csv_export_import",
      "ts": "2026-06-02T00:00:00Z"
    },
    {
      "leadId": "csv-door-204",
      "repName": "Michael McCarthy",
      "status": "No Answer",
      "isCA": false,
      "date": "2026-06-02",
      "address": "",
      "eventType": "csv_export_import",
      "ts": "2026-06-02T00:00:00Z"
    },
    {
      "leadId": "csv-door-205",
      "repName": "Michael McCarthy",
      "status": "No Answer",
      "isCA": false,
      "date": "2026-06-02",
      "address": "",
      "eventType": "csv_export_import",
      "ts": "2026-06-02T00:00:00Z"
    },
    {
      "leadId": "csv-door-206",
      "repName": "Michael McCarthy",
      "status": "No Answer",
      "isCA": false,
      "date": "2026-06-02",
      "address": "",
      "eventType": "csv_export_import",
      "ts": "2026-06-02T00:00:00Z"
    },
    {
      "leadId": "csv-door-207",
      "repName": "Michael McCarthy",
      "status": "No Answer",
      "isCA": false,
      "date": "2026-06-02",
      "address": "",
      "eventType": "csv_export_import",
      "ts": "2026-06-02T00:00:00Z"
    },
    {
      "leadId": "csv-door-208",
      "repName": "Michael McCarthy",
      "status": "No Answer",
      "isCA": false,
      "date": "2026-06-02",
      "address": "",
      "eventType": "csv_export_import",
      "ts": "2026-06-02T00:00:00Z"
    },
    {
      "leadId": "csv-door-209",
      "repName": "Michael McCarthy",
      "status": "No Answer",
      "isCA": false,
      "date": "2026-06-02",
      "address": "",
      "eventType": "csv_export_import",
      "ts": "2026-06-02T00:00:00Z"
    },
    {
      "leadId": "csv-door-210",
      "repName": "Michael McCarthy",
      "status": "No Answer",
      "isCA": false,
      "date": "2026-06-02",
      "address": "",
      "eventType": "csv_export_import",
      "ts": "2026-06-02T00:00:00Z"
    },
    {
      "leadId": "csv-door-211",
      "repName": "Michael McCarthy",
      "status": "No Answer",
      "isCA": false,
      "date": "2026-06-02",
      "address": "",
      "eventType": "csv_export_import",
      "ts": "2026-06-02T00:00:00Z"
    },
    {
      "leadId": "csv-door-212",
      "repName": "George Bechara",
      "status": "No Answer",
      "isCA": false,
      "date": "2026-06-02",
      "address": "",
      "eventType": "csv_export_import",
      "ts": "2026-06-02T00:00:00Z"
    },
    {
      "leadId": "csv-door-213",
      "repName": "George Bechara",
      "status": "No Answer",
      "isCA": false,
      "date": "2026-06-02",
      "address": "",
      "eventType": "csv_export_import",
      "ts": "2026-06-02T00:00:00Z"
    },
    {
      "leadId": "csv-door-214",
      "repName": "George Bechara",
      "status": "No Answer",
      "isCA": false,
      "date": "2026-06-02",
      "address": "",
      "eventType": "csv_export_import",
      "ts": "2026-06-02T00:00:00Z"
    },
    {
      "leadId": "csv-door-215",
      "repName": "George Bechara",
      "status": "No Answer",
      "isCA": false,
      "date": "2026-06-02",
      "address": "",
      "eventType": "csv_export_import",
      "ts": "2026-06-02T00:00:00Z"
    },
    {
      "leadId": "csv-door-216",
      "repName": "George Bechara",
      "status": "No Answer",
      "isCA": false,
      "date": "2026-06-02",
      "address": "",
      "eventType": "csv_export_import",
      "ts": "2026-06-02T00:00:00Z"
    },
    {
      "leadId": "csv-door-217",
      "repName": "George Bechara",
      "status": "No Answer",
      "isCA": false,
      "date": "2026-06-02",
      "address": "",
      "eventType": "csv_export_import",
      "ts": "2026-06-02T00:00:00Z"
    },
    {
      "leadId": "csv-door-218",
      "repName": "George Bechara",
      "status": "No Answer",
      "isCA": false,
      "date": "2026-06-02",
      "address": "",
      "eventType": "csv_export_import",
      "ts": "2026-06-02T00:00:00Z"
    },
    {
      "leadId": "csv-door-219",
      "repName": "George Bechara",
      "status": "No Answer",
      "isCA": false,
      "date": "2026-06-02",
      "address": "",
      "eventType": "csv_export_import",
      "ts": "2026-06-02T00:00:00Z"
    },
    {
      "leadId": "csv-door-220",
      "repName": "Andrew Prickel",
      "status": "No Answer",
      "isCA": false,
      "date": "2026-06-02",
      "address": "",
      "eventType": "csv_export_import",
      "ts": "2026-06-02T00:00:00Z"
    },
    {
      "leadId": "csv-door-221",
      "repName": "Andrew Prickel",
      "status": "No Answer",
      "isCA": false,
      "date": "2026-06-02",
      "address": "",
      "eventType": "csv_export_import",
      "ts": "2026-06-02T00:00:00Z"
    },
    {
      "leadId": "csv-door-222",
      "repName": "Andrew Prickel",
      "status": "No Answer",
      "isCA": false,
      "date": "2026-06-02",
      "address": "",
      "eventType": "csv_export_import",
      "ts": "2026-06-02T00:00:00Z"
    },
    {
      "leadId": "csv-door-223",
      "repName": "Marc Mitchell",
      "status": "No Answer",
      "isCA": false,
      "date": "2026-06-02",
      "address": "",
      "eventType": "csv_export_import",
      "ts": "2026-06-02T00:00:00Z"
    },
    {
      "leadId": "csv-door-224",
      "repName": "Isabelle Price",
      "status": "No Answer",
      "isCA": false,
      "date": "2026-06-02",
      "address": "",
      "eventType": "csv_export_import",
      "ts": "2026-06-02T00:00:00Z"
    },
    {
      "leadId": "csv-ca-225",
      "repName": "Marc Mitchell",
      "status": "ICA",
      "isCA": true,
      "date": "2026-06-02",
      "address": "",
      "eventType": "csv_export_import",
      "ts": "2026-06-02T00:00:00Z"
    },
    {
      "leadId": "csv-ca-226",
      "repName": "Christian Brown",
      "status": "ICA",
      "isCA": true,
      "date": "2026-06-02",
      "address": "",
      "eventType": "csv_export_import",
      "ts": "2026-06-02T00:00:00Z"
    },
    {
      "leadId": "csv-ca-227",
      "repName": "Andrew Funk",
      "status": "ICA",
      "isCA": true,
      "date": "2026-06-02",
      "address": "",
      "eventType": "csv_export_import",
      "ts": "2026-06-02T00:00:00Z"
    },
    {
      "leadId": "csv-ca-228",
      "repName": "David Kerns",
      "status": "ICA",
      "isCA": true,
      "date": "2026-06-02",
      "address": "",
      "eventType": "csv_export_import",
      "ts": "2026-06-02T00:00:00Z"
    },
    {
      "leadId": "47207",
      "repName": "Andrew Funk",
      "status": "NOT INTERRESTED",
      "isCA": false,
      "date": "2026-06-02",
      "address": "7802 Lobelia Ln, Springfield, VA",
      "ts": "2026-06-02T16:43:38.285Z"
    },
    {
      "leadId": "47208",
      "repName": "Andrew Funk",
      "status": "NO ANSWER",
      "isCA": false,
      "date": "2026-06-02",
      "address": "7800 Lobelia Ln, Springfield, VA",
      "ts": "2026-06-02T16:43:47.998Z"
    }
  ]
}